behavysis_pipeline/__init__.py
behavysis_pipeline/behav_classifier/__init__.py
behavysis_pipeline/behav_classifier/behav_classifier.py
behavysis_pipeline/behav_classifier/clf_models/__init__.py
behavysis_pipeline/behav_classifier/clf_models/base_torch_model.py
behavysis_pipeline/behav_classifier/clf_models/clf_templates.py
behavysis_pipeline/pipeline/__init__.py
behavysis_pipeline/pipeline/experiment.py
behavysis_pipeline/pipeline/project.py
behavysis_pipeline/processes/__init__.py
behavysis_pipeline/processes/analyse.py
behavysis_pipeline/processes/analyse_behavs.py
behavysis_pipeline/processes/analyse_combine.py
behavysis_pipeline/processes/calculate_params.py
behavysis_pipeline/processes/classify_behavs.py
behavysis_pipeline/processes/evaluate/__init__.py
behavysis_pipeline/processes/evaluate/evaluate_vid_funcs.py
behavysis_pipeline/processes/export.py
behavysis_pipeline/processes/extract_features.py
behavysis_pipeline/processes/format_vid.py
behavysis_pipeline/processes/preprocess.py
behavysis_pipeline/processes/run_dlc.py
behavysis_pipeline/processes/update_configs.py
behavysis_pipeline/scripts/__init__.py
behavysis_pipeline/scripts/classifier_gui.py
behavysis_pipeline/scripts/make_classifier.py
behavysis_pipeline/scripts/make_project.py
behavysis_pipeline/scripts/project_gui.py
behavysis_pipeline/templates/default_configs.json
behavysis_pipeline/templates/dlc_subproc.py
behavysis_pipeline/templates/run_project.py
behavysis_pipeline/templates/simba_subproc.py
behavysis_pipeline/templates/train_behav_classifier.py
behavysis_pipeline/utils/__init__.py
behavysis_pipeline/utils/dask_utils.py
behavysis_pipeline-0.1.24.dist-info/LICENSE
behavysis_pipeline-0.1.24.dist-info/METADATA
behavysis_pipeline-0.1.24.dist-info/WHEEL
behavysis_pipeline-0.1.24.dist-info/entry_points.txt
behavysis_pipeline-0.1.24.dist-info/RECORD
