Metadata-Version: 2.1
Name: behavysis_pipeline
Version: 0.1.24
Summary: An animal behaviour processing and analysis package
Home-page: https://tlee08.github.io/behavysis_pipeline
License: LGPL-3.0-or-later
Author: BowenLab
Requires-Python: >=3.12,<3.13
Classifier: License :: OSI Approved :: GNU Lesser General Public License v3 or later (LGPLv3+)
Classifier: Programming Language :: Python :: 3
Classifier: Programming Language :: Python :: 3.12
Requires-Dist: Jinja2 (>=3.1.4,<4.0.0)
Requires-Dist: PySide6 (>=6.8.0.2,<7.0.0.0)
Requires-Dist: behavysis_core (>=0.1.24,<0.2.0)
Requires-Dist: dask[complete] (>=2024.10.0,<2025.0.0)
Requires-Dist: graphviz (>=0.20.3,<0.21.0)
Requires-Dist: imbalanced-learn (>=0.12.2,<0.13.0)
Requires-Dist: pyqtgraph (>=0.13.7,<0.14.0)
Requires-Dist: scikit-learn (>=1.4.2,<2.0.0)
Requires-Dist: streamlit (>=1.36.0,<2.0.0)
Requires-Dist: torch (>=2.2,<2.3)
Project-URL: Documentation, https://tlee08.github.io/behavysis_pipeline
Project-URL: Repository, https://github.com/tlee08/behavysis_pipeline
